odoo/addons/website_transfer_payment_mode/README.rst
odoo/addons/website_transfer_payment_mode/__init__.py
odoo/addons/website_transfer_payment_mode/__manifest__.py
odoo/addons/website_transfer_payment_mode/models/__init__.py
odoo/addons/website_transfer_payment_mode/models/payment_acquirer.py
odoo/addons/website_transfer_payment_mode/models/sale.py
odoo/addons/website_transfer_payment_mode/static/description/icon.png
odoo/addons/website_transfer_payment_mode/views/payment_views.xml
odoo_addon_website_transfer_payment_mode-17.0.1.0.0.dist-info/METADATA
odoo_addon_website_transfer_payment_mode-17.0.1.0.0.dist-info/WHEEL
odoo_addon_website_transfer_payment_mode-17.0.1.0.0.dist-info/top_level.txt
odoo_addon_website_transfer_payment_mode-17.0.1.0.0.dist-info/RECORD
