Metadata-Version: 2.1
Name: odoo-addon-website_transfer_payment_mode
Version: 17.0.1.0.0
Requires-Python: >=3.10
Requires-Dist: odoo-addon-account_payment_sale>=17.0dev,<17.1dev
Requires-Dist: odoo>=17.0a,<17.1dev
Summary: Transfer payment mode from website to SO.
Home-page: https://github.com/sygel-technology/sy-e-commerce
Author: Sygel
Classifier: Programming Language :: Python
Classifier: Framework :: Odoo
Classifier: Framework :: Odoo :: 17.0
